phpipam_exporter/__init__.py
phpipam_exporter/cli.py
phpipam_exporter/libs/__init__.py
phpipam_exporter/libs/api.py
phpipam_exporter/libs/ipam.py
phpipam_exporter/templates/dhcpd.j2
phpipam_exporter/templates/dnsmasq.j2
phpipam_exporter/templates/hosts.j2
phpipam_exporter/templates/json.j2
phpipam_exporter-0.5.1.dist-info/entry_points.txt
phpipam_exporter-0.5.1.dist-info/LICENSE
phpipam_exporter-0.5.1.dist-info/WHEEL
phpipam_exporter-0.5.1.dist-info/METADATA
phpipam_exporter-0.5.1.dist-info/RECORD
