Metadata-Version: 2.1
Name: phpipam-exporter
Version: 0.5.1
Summary: Top-level package for phpipam-exporter.
Home-page: https://github.com/BlackSmith/phpipam_exporter
License: MIT
Author: Martin Korbel
Author-email: git@blackserver.cz
Requires-Python: >=3.7,<4
Classifier: Intended Audience :: Developers
Classifier: License :: OSI Approved :: MIT License
Classifier: Programming Language :: Python :: 3
Classifier: Programming Language :: Python :: 3.10
Classifier: Programming Language :: Python :: 3.7
Classifier: Programming Language :: Python :: 3.8
Classifier: Programming Language :: Python :: 3.9
Requires-Dist: Jinja2 (>=3.0.1,<4.0.0)
Requires-Dist: certifi (>=2020.12.5,<2021.0.0)
Requires-Dist: click
Requires-Dist: requests (>=2.25.1,<3.0.0)
Requires-Dist: urllib3 (>=1.26.0,<2.0.0)
